graphics_creator.py
graphics_creator-1.0.1.dist-info/WHEEL
graphics_creator-1.0.1.dist-info/METADATA
graphics_creator-1.0.1.dist-info/RECORD
